bottle_sql/__init__.py
bottle_sql/bottle_sql.py
bottle_sql-0.0.2.dist-info/LICENSE.txt
bottle_sql-0.0.2.dist-info/METADATA
bottle_sql-0.0.2.dist-info/WHEEL
bottle_sql-0.0.2.dist-info/top_level.txt
bottle_sql-0.0.2.dist-info/RECORD
