Metadata-Version: 2.1
Name: bottle-sql
Version: 0.0.2
Summary: SQL plugin for Bottle
Author-email: TJ Renninger <renninger12@gmail.com>
Classifier: Programming Language :: Python :: 3
Classifier: License :: OSI Approved :: MIT License
Classifier: Operating System :: OS Independent
Requires-Python: >=3.8
License-File: LICENSE.txt
Requires-Dist: bottle
Requires-Dist: pymysql
